grepy/__init__.py
grepy/cli.py
grepy/grep.py
lr_grepy-0.1.0.dist-info/LICENSE
lr_grepy-0.1.0.dist-info/METADATA
lr_grepy-0.1.0.dist-info/WHEEL
lr_grepy-0.1.0.dist-info/entry_points.txt
lr_grepy-0.1.0.dist-info/top_level.txt
lr_grepy-0.1.0.dist-info/RECORD
