Metadata-Version: 2.1
Name: lr-grepy
Version: 0.1.0
Summary: An example project's grep-like CLI app         implemented in Python.
Home-page: https://github.com/Literank/lr_grepy
Author: literank
License: MIT
Platform: UNKNOWN
License-File: LICENSE
